{
        "date": "2025/01/21 05:00 GMT+8",
        "rates": {
                "ADA": 6.9021,
                "AED": 1.9878,
                "AFN": 0.0995,
                "ALL": 0.0772,
                "AMD": 0.0183,
                "ANG": 4.0605,
                "AOA": 0.0079,
                "ARS": 0.007,
                "ATS": 0.5526,
                "AUD": 4.5786,
                "AWG": 4.0784,
                "AZM": 0.0009,
                "AZN": 4.293,
                "BAM": 3.8878,
                "BBD": 3.6502,
                "BCH": 3192.7461,
                "BDT": 0.0599,
                "BEF": 0.1885,
                "BGN": 3.8878,
                "BHD": 19.4157,
                "BIF": 0.0025,
                "BMD": 7.3003,
                "BND": 5.3853,
                "BOB": 1.0569,
                "BRL": 1.2107,
                "BSD": 7.3003,
                "BTC": 757575.7576,
                "BTN": 0.0847,
                "BWP": 0.5223,
                "BYN": 2.2325,
                "BYR": 0.0002,
                "BZD": 3.628,
                "CAD": 5.103,
                "CDF": 0.0026,
                "CHF": 8.053,
                "CLF": 280.1301,
                "CLP": 0.0072,
                "CNH": 1.0049,
                "CNY": 1.0,
                "COP": 0.0017,
                "CRC": 0.0145,
                "CUC": 7.3003,
                "CUP": 0.3041,
                "CVE": 0.069,
                "CYP": 12.992,
                "CZK": 0.3016,
                "DEM": 3.8878,
                "DJF": 0.041,
                "DKK": 1.0191,
                "DOGE": 2.6604,
                "DOP": 0.119,
                "DOT": 47.1817,
                "DZD": 0.054,
                "EEK": 0.486,
                "EGP": 0.1451,
                "ERN": 0.4867,
                "ESP": 0.0457,
                "ETB": 0.0574,
                "ETH": 24301.3366,
                "EUR": 7.6039,
                "FIM": 1.2789,
                "FJD": 3.1422,
                "FKP": 9.0002,
                "FRF": 1.1592,
                "GBP": 9.0002,
                "GEL": 2.5625,
                "GGP": 9.0002,
                "GHC": 0.0,
                "GHS": 0.4875,
                "GIP": 9.0002,
                "GMD": 0.1014,
                "GNF": 0.0008,
                "GRD": 0.0223,
                "GTQ": 0.9456,
                "GYD": 0.035,
                "HKD": 0.9382,
                "HNL": 0.2869,
                "HRK": 1.0092,
                "HTG": 0.0559,
                "HUF": 0.0185,
                "IDR": 0.0004,
                "IEP": 9.6549,
                "ILS": 2.0464,
                "IMP": 9.0002,
                "INR": 0.0847,
                "IQD": 0.0056,
                "IRR": 0.0002,
                "ISK": 0.0521,
                "ITL": 0.0039,
                "JEP": 9.0002,
                "JMD": 0.0463,
                "JOD": 10.2966,
                "JPY": 0.0469,
                "KES": 0.0564,
                "KGS": 0.0835,
                "KHR": 0.0018,
                "KMF": 0.0155,
                "KPW": 0.0081,
                "KRW": 0.0051,
                "KWD": 23.686,
                "KYD": 8.8314,
                "KZT": 0.0138,
                "LAK": 0.0003,
                "LBP": 0.0001,
                "LINK": 187.1639,
                "LKR": 0.0246,
                "LRD": 0.0384,
                "LSL": 0.3942,
                "LTC": 877.7088,
                "LTL": 2.2022,
                "LUF": 0.1885,
                "LUNA": 2.3856,
                "LVL": 10.8194,
                "LYD": 1.4758,
                "MAD": 0.7296,
                "MDL": 0.3892,
                "MGA": 0.0016,
                "MGF": 0.0003,
                "MKD": 0.1223,
                "MMK": 0.0035,
                "MNT": 0.0021,
                "MOP": 0.9109,
                "MRO": 0.0184,
                "MRU": 0.1837,
                "MTL": 17.7123,
                "MUR": 0.156,
                "MVR": 0.4729,
                "MWK": 0.0042,
                "MXN": 0.356,
                "MXV": 2.9723,
                "MYR": 1.6244,
                "MZM": 0.0001,
                "MZN": 0.1142,
                "NAD": 0.3942,
                "NGN": 0.0047,
                "NIO": 0.1984,
                "NLG": 3.4505,
                "NOK": 0.6461,
                "NPR": 0.0529,
                "NZD": 4.1425,
                "OMR": 18.9653,
                "PAB": 7.3003,
                "PEN": 1.9486,
                "PGK": 1.795,
                "PHP": 0.1254,
                "PKR": 0.0262,
                "PLN": 1.7886,
                "PTE": 0.0379,
                "PYG": 0.0009,
                "QAR": 2.0056,
                "ROL": 0.0002,
                "RON": 1.5278,
                "RSD": 0.0649,
                "RUB": 0.0723,
                "RWF": 0.0052,
                "SAR": 1.9468,
                "SBD": 0.8616,
                "SCR": 0.5115,
                "SDD": 0.0001,
                "SDG": 0.0121,
                "SEK": 0.6623,
                "SGD": 5.3853,
                "SHP": 9.0002,
                "SIT": 0.0317,
                "SKK": 0.2524,
                "SLE": 0.3203,
                "SLL": 0.0003,
                "SOS": 0.0128,
                "SPL": 43.8019,
                "SRD": 0.2071,
                "SRG": 0.0002,
                "STD": 0.0003,
                "STN": 0.3072,
                "SVC": 0.8343,
                "SYP": 0.0006,
                "SZL": 0.3942,
                "THB": 0.2139,
                "TJS": 0.6685,
                "TMM": 0.0004,
                "TMT": 2.086,
                "TND": 2.2863,
                "TOP": 3.003,
                "TRL": 0.0,
                "TRY": 0.2052,
                "TTD": 1.075,
                "TVD": 4.5786,
                "TWD": 0.2235,
                "TZS": 0.0029,
                "UAH": 0.1731,
                "UGX": 0.002,
                "UNI": 100.0269,
                "USD": 7.3003,
                "UYU": 0.166,
                "UZS": 0.0006,
                "VAL": 0.0039,
                "VEB": 0.0,
                "VED": 0.1329,
                "VEF": 0.0,
                "VES": 0.1329,
                "VND": 0.0003,
                "VUV": 0.0586,
                "WST": 2.5675,
                "XAF": 0.0116,
                "XAG": 223.1241,
                "XAU": 19774.5699,
                "XBT": 757575.7576,
                "XCD": 2.698,
                "XDR": 9.4854,
                "XLM": 3.2837,
                "XOF": 0.0116,
                "XPD": 6866.2455,
                "XPF": 0.0637,
                "XPT": 6907.5085,
                "XRP": 23.0143,
                "YER": 0.0293,
                "ZAR": 0.3942,
                "ZMK": 0.0003,
                "ZMW": 0.2622,
                "ZWD": 0.0202,
                "ZWG": 0.2783,
                "ZWL": 0.0001
        }
}