{
  "date": "2025-08-13 22:00 GMT+8",
  "rates": {
    "ADA": 6.37968,
    "AED": 1.9535,
    "AFN": 0.10508,
    "ALL": 0.08634,
    "AMD": 0.01877,
    "ANG": 3.97944,
    "AOA": 0.00784,
    "ARS": 0.00542,
    "ATS": 0.61011,
    "AUD": 4.69784,
    "AWG": 4.00795,
    "AZM": 0.00084,
    "AZN": 4.22013,
    "BAM": 4.29245,
    "BBD": 3.58711,
    "BCH": 4498.2232,
    "BDT": 0.05902,
    "BEF": 0.20811,
    "BGN": 4.29245,
    "BHD": 19.08039,
    "BIF": 0.00241,
    "BMD": 7.17423,
    "BND": 5.6043,
    "BOB": 1.0368,
    "BRL": 1.32922,
    "BSD": 7.17423,
    "BTC": 877192.98246,
    "BTN": 0.082,
    "BWP": 0.51345,
    "BYN": 2.17061,
    "BYR": 0.00022,
    "BZD": 3.56209,
    "CAD": 5.21225,
    "CDF": 0.00246,
    "CHF": 8.9153,
    "CLF": 295.16636,
    "CLP": 0.00754,
    "CNH": 0.99936,
    "CNY": 1,
    "COP": 0.00178,
    "CRC": 0.01418,
    "CUC": 7.17423,
    "CUP": 0.29881,
    "CVE": 0.07613,
    "CYP": 14.34422,
    "CZK": 0.34319,
    "DEM": 4.29245,
    "DJF": 0.04032,
    "DKK": 1.12495,
    "DOGE": 1.74952,
    "DOP": 0.11718,
    "DOT": 30.50626,
    "DZD": 0.05525,
    "EEK": 0.53656,
    "EGP": 0.14841,
    "ERN": 0.47828,
    "ESP": 0.05046,
    "ETB": 0.05119,
    "ETH": 33500.83752,
    "EUR": 8.3953,
    "EURC": 8.40164,
    "FIM": 1.41199,
    "FJD": 3.19188,
    "FKP": 9.73766,
    "FRF": 1.27985,
    "GBP": 9.73766,
    "GEL": 2.63541,
    "GGP": 9.73766,
    "GHC": 7e-05,
    "GHS": 0.67524,
    "GIP": 9.73766,
    "GMD": 0.09873,
    "GNF": 0.00083,
    "GRD": 0.02464,
    "GTQ": 0.93513,
    "GYD": 0.03428,
    "HKD": 0.91392,
    "HNL": 0.2738,
    "HRK": 1.11425,
    "HTG": 0.05471,
    "HUF": 0.02122,
    "IDR": 0.00045,
    "IEP": 10.65983,
    "ILS": 2.11869,
    "IMP": 9.73766,
    "INR": 0.082,
    "IQD": 0.00547,
    "IRR": 0.00017,
    "ISK": 0.05863,
    "ITL": 0.00434,
    "JEP": 9.73766,
    "JMD": 0.04477,
    "JOD": 10.1188,
    "JPY": 0.04872,
    "KES": 0.05552,
    "KGS": 0.0821,
    "KHR": 0.00179,
    "KMF": 0.01706,
    "KPW": 0.00797,
    "KRW": 0.00521,
    "KWD": 23.4872,
    "KYD": 8.62393,
    "KZT": 0.01333,
    "LAK": 0.00033,
    "LBP": 8e-05,
    "LINK": 169.60047,
    "LKR": 0.02383,
    "LRD": 0.03577,
    "LSL": 0.40942,
    "LTC": 944.79559,
    "LTL": 2.43145,
    "LUF": 0.20811,
    "LUNA": 1.15095,
    "LVL": 11.9455,
    "LYD": 1.31975,
    "MAD": 0.79651,
    "MDL": 0.42881,
    "MGA": 0.00163,
    "MGF": 0.00033,
    "MKD": 0.13608,
    "MMK": 0.00342,
    "MNT": 0.002,
    "MOP": 0.88731,
    "MRO": 0.01801,
    "MRU": 0.18011,
    "MTL": 19.56214,
    "MUR": 0.15787,
    "MVR": 0.46475,
    "MWK": 0.00414,
    "MXN": 0.38582,
    "MXV": 3.29308,
    "MYR": 1.70516,
    "MZM": 0.00011,
    "MZN": 0.1123,
    "NAD": 0.40978,
    "NGN": 0.00468,
    "NIO": 0.1949,
    "NLG": 3.81086,
    "NOK": 0.70426,
    "NPR": 0.05123,
    "NZD": 4.29123,
    "OMR": 18.64003,
    "PAB": 7.17423,
    "PEN": 2.03442,
    "PGK": 1.69869,
    "PHP": 0.1266,
    "PKR": 0.02528,
    "PLN": 1.97361,
    "PTE": 0.04189,
    "PYG": 0.00096,
    "QAR": 1.97094,
    "ROL": 0.00017,
    "RON": 1.65902,
    "RSD": 0.07168,
    "RUB": 0.09011,
    "RWF": 0.00497,
    "SAR": 1.91313,
    "SBD": 0.84412,
    "SCR": 0.49461,
    "SDD": 0.00012,
    "SDG": 0.01195,
    "SEK": 0.75224,
    "SGD": 5.60514,
    "SHP": 9.73805,
    "SIT": 0.03504,
    "SKK": 0.27876,
    "SLE": 0.31542,
    "SLL": 0.00032,
    "SOL": 1457.89596,
    "SOS": 0.01255,
    "SPL": 43.04536,
    "SRD": 0.19095,
    "SRG": 0.00019,
    "STD": 0.00034,
    "STN": 0.33898,
    "SVC": 0.81991,
    "SYP": 0.00055,
    "SZL": 0.40978,
    "THB": 0.22252,
    "TJS": 0.76903,
    "TMM": 0.00041,
    "TMT": 2.04615,
    "TND": 2.49561,
    "TOP": 2.98216,
    "TRL": 0,
    "TRY": 0.17611,
    "TTD": 1.05655,
    "TVD": 4.69863,
    "TWD": 0.2399,
    "TZS": 0.00279,
    "UAH": 0.17314,
    "UGX": 0.00202,
    "UNI": 86.98171,
    "USD": 7.17423,
    "USDC": 7.18256,
    "USDP": 7.19109,
    "UYU": 0.17929,
    "UZS": 0.00057,
    "VAL": 0.00434,
    "VEB": 0,
    "VED": 0.05397,
    "VEF": 0,
    "VES": 0.05397,
    "VND": 0.00027,
    "VUV": 0.06005,
    "WST": 2.69896,
    "XAF": 0.0128,
    "XAG": 276.08065,
    "XAU": 24142.92612,
    "XBT": 869565.21739,
    "XCD": 2.6503,
    "XCG": 3.97959,
    "XDR": 9.78967,
    "XLM": 3.26379,
    "XOF": 0.0128,
    "XPD": 8124.13681,
    "XPF": 0.07038,
    "XPT": 9626.49211,
    "XRP": 23.6713,
    "YER": 0.02986,
    "ZAR": 0.40978,
    "ZMK": 0.00031,
    "ZMW": 0.30977,
    "ZWD": 0.01982,
    "ZWG": 0.26804,
    "ZWL": 0.00011
  }
}
