{
  "date": "2025-07-22 07:00 GMT+8",
  "rates": {
    "ADA": 6.45803,
    "AED": 1.9539,
    "AFN": 0.10399,
    "ALL": 0.08603,
    "AMD": 0.01875,
    "ANG": 3.98375,
    "AOA": 0.00782,
    "ARS": 0.00563,
    "ATS": 0.60984,
    "AUD": 4.6812,
    "AWG": 4.00877,
    "AZM": 0.00084,
    "AZN": 4.21826,
    "BAM": 4.29053,
    "BBD": 3.58785,
    "BCH": 3749.81251,
    "BDT": 0.05904,
    "BEF": 0.20802,
    "BGN": 4.29053,
    "BHD": 19.0843,
    "BIF": 0.00241,
    "BMD": 7.1757,
    "BND": 5.60463,
    "BOB": 1.03856,
    "BRL": 1.28912,
    "BSD": 7.1757,
    "BTC": 840336.13445,
    "BTN": 0.08321,
    "BWP": 0.51591,
    "BYN": 2.1915,
    "BYR": 0.00022,
    "BZD": 3.56672,
    "CAD": 5.24519,
    "CDF": 0.00247,
    "CHF": 8.99121,
    "CLF": 288.61195,
    "CLP": 0.00752,
    "CNH": 1.00067,
    "CNY": 1,
    "COP": 0.00178,
    "CRC": 0.01423,
    "CUC": 7.1757,
    "CUP": 0.29913,
    "CVE": 0.0761,
    "CYP": 14.33781,
    "CZK": 0.34075,
    "DEM": 4.29053,
    "DJF": 0.04035,
    "DKK": 1.12412,
    "DOGE": 1.95298,
    "DOP": 0.11884,
    "DOT": 32.31503,
    "DZD": 0.05517,
    "EEK": 0.5363,
    "EGP": 0.1457,
    "ERN": 0.47838,
    "ESP": 0.05043,
    "ETB": 0.05166,
    "ETH": 27041.64413,
    "EUR": 8.39123,
    "EURC": 8.39439,
    "FIM": 1.4113,
    "FJD": 3.18411,
    "FKP": 9.6787,
    "FRF": 1.27924,
    "GBP": 9.6787,
    "GEL": 2.64844,
    "GGP": 9.6787,
    "GHC": 7e-05,
    "GHS": 0.688,
    "GIP": 9.6787,
    "GMD": 0.09953,
    "GNF": 0.00083,
    "GRD": 0.02463,
    "GTQ": 0.93495,
    "GYD": 0.0343,
    "HKD": 0.91416,
    "HNL": 0.27422,
    "HRK": 1.11371,
    "HTG": 0.05469,
    "HUF": 0.02103,
    "IDR": 0.00044,
    "IEP": 10.65467,
    "ILS": 2.14307,
    "IMP": 9.6787,
    "INR": 0.08322,
    "IQD": 0.00548,
    "IRR": 0.00017,
    "ISK": 0.05893,
    "ITL": 0.00433,
    "JEP": 9.6787,
    "JMD": 0.04489,
    "JOD": 10.12087,
    "JPY": 0.04869,
    "KES": 0.05547,
    "KGS": 0.08204,
    "KHR": 0.00179,
    "KMF": 0.01706,
    "KPW": 0.00797,
    "KRW": 0.00519,
    "KWD": 23.5007,
    "KYD": 8.65275,
    "KZT": 0.01353,
    "LAK": 0.00033,
    "LBP": 8e-05,
    "LINK": 140.28689,
    "LKR": 0.0238,
    "LRD": 0.03577,
    "LSL": 0.40729,
    "LTC": 832.3276,
    "LTL": 2.43027,
    "LUF": 0.20801,
    "LUNA": 1.1377,
    "LVL": 11.93972,
    "LYD": 1.32151,
    "MAD": 0.79469,
    "MDL": 0.42227,
    "MGA": 0.00162,
    "MGF": 0.00032,
    "MKD": 0.13601,
    "MMK": 0.00342,
    "MNT": 0.002,
    "MOP": 0.88753,
    "MRO": 0.01805,
    "MRU": 0.18046,
    "MTL": 19.54632,
    "MUR": 0.15709,
    "MVR": 0.46477,
    "MWK": 0.00414,
    "MXN": 0.38423,
    "MXV": 3.27261,
    "MYR": 1.69425,
    "MZM": 0.00011,
    "MZN": 0.11234,
    "NAD": 0.40729,
    "NGN": 0.00469,
    "NIO": 0.195,
    "NLG": 3.80778,
    "NOK": 0.70635,
    "NPR": 0.05199,
    "NZD": 4.28181,
    "OMR": 18.64343,
    "PAB": 7.1757,
    "PEN": 2.01566,
    "PGK": 1.73155,
    "PHP": 0.12583,
    "PKR": 0.02511,
    "PLN": 1.97696,
    "PTE": 0.04186,
    "PYG": 0.00092,
    "QAR": 1.97135,
    "ROL": 0.00017,
    "RON": 1.65534,
    "RSD": 0.07164,
    "RUB": 0.09176,
    "RWF": 0.00498,
    "SAR": 1.91352,
    "SBD": 0.85232,
    "SCR": 0.48911,
    "SDD": 0.00012,
    "SDG": 0.01195,
    "SEK": 0.74915,
    "SGD": 5.60482,
    "SHP": 9.6787,
    "SIT": 0.03502,
    "SKK": 0.27854,
    "SLE": 0.31564,
    "SLL": 0.00032,
    "SOL": 1414.92748,
    "SOS": 0.01258,
    "SPL": 43.05418,
    "SRD": 0.19497,
    "SRG": 0.00019,
    "STD": 0.00034,
    "STN": 0.33991,
    "SVC": 0.82008,
    "SYP": 0.00055,
    "SZL": 0.40729,
    "THB": 0.22267,
    "TJS": 0.75117,
    "TMM": 0.00041,
    "TMT": 2.04443,
    "TND": 2.48554,
    "TOP": 3.00595,
    "TRL": 0,
    "TRY": 0.17753,
    "TTD": 1.05705,
    "TVD": 4.68108,
    "TWD": 0.24437,
    "TZS": 0.00275,
    "UAH": 0.17178,
    "UGX": 0.002,
    "UNI": 77.79776,
    "USD": 7.1757,
    "USDC": 7.20301,
    "USDP": 7.16709,
    "UYU": 0.17794,
    "UZS": 0.00057,
    "VAL": 0.00433,
    "VEB": 0,
    "VED": 0.06069,
    "VEF": 0,
    "VES": 0.06069,
    "VND": 0.00027,
    "VUV": 0.06035,
    "WST": 2.60771,
    "XAF": 0.01279,
    "XAG": 279.49981,
    "XAU": 24390.2439,
    "XBT": 840336.13445,
    "XCD": 2.6517,
    "XCG": 3.98407,
    "XDR": 9.8053,
    "XLM": 3.39041,
    "XOF": 0.01279,
    "XPD": 9100.0091,
    "XPF": 0.07032,
    "XPT": 10401.49782,
    "XRP": 25.60852,
    "YER": 0.02978,
    "ZAR": 0.40729,
    "ZMK": 0.00031,
    "ZMW": 0.31064,
    "ZWD": 0.01983,
    "ZWG": 0.26718,
    "ZWL": 0.00011
  }
}
