{
        "date": "2024/12/13 19:00 GMT+8",
        "rates": {
                "ADA": 8.0244,
                "AED": 1.981,
                "AFN": 0.104,
                "ALL": 0.0777,
                "AMD": 0.0184,
                "ANG": 4.0453,
                "AOA": 0.0079,
                "ARS": 0.0071,
                "ATS": 0.5544,
                "AUD": 4.6357,
                "AWG": 4.0643,
                "AZM": 0.0009,
                "AZN": 4.2795,
                "BAM": 3.9007,
                "BBD": 3.6375,
                "BCH": 3870.1188,
                "BDT": 0.0608,
                "BEF": 0.1891,
                "BGN": 3.9007,
                "BHD": 19.3485,
                "BIF": 0.0025,
                "BMD": 7.2751,
                "BND": 5.3961,
                "BOB": 1.0521,
                "BRL": 1.2069,
                "BSD": 7.2751,
                "BTC": 729927.0073,
                "BTN": 0.0858,
                "BWP": 0.5349,
                "BYN": 2.2248,
                "BYR": 0.0002,
                "BZD": 3.5997,
                "CAD": 5.1152,
                "CDF": 0.0026,
                "CHF": 8.1379,
                "CLF": 285.1944,
                "CLP": 0.0074,
                "CNH": 0.9989,
                "CNY": 1.0,
                "COP": 0.0017,
                "CRC": 0.0144,
                "CUC": 7.2751,
                "CUP": 0.3028,
                "CVE": 0.0692,
                "CYP": 13.0351,
                "CZK": 0.3046,
                "DEM": 3.9007,
                "DJF": 0.0409,
                "DKK": 1.0229,
                "DOGE": 2.9645,
                "DOP": 0.1199,
                "DOT": 65.8286,
                "DZD": 0.0543,
                "EEK": 0.4876,
                "EGP": 0.1431,
                "ERN": 0.485,
                "ESP": 0.0459,
                "ETB": 0.0573,
                "ETH": 28392.9585,
                "EUR": 7.6291,
                "FIM": 1.2831,
                "FJD": 3.1381,
                "FKP": 9.1998,
                "FRF": 1.1631,
                "GBP": 9.1998,
                "GEL": 2.5795,
                "GGP": 9.1998,
                "GHC": 0.0,
                "GHS": 0.4947,
                "GIP": 9.1998,
                "GMD": 0.1007,
                "GNF": 0.0008,
                "GRD": 0.0224,
                "GTQ": 0.9439,
                "GYD": 0.0348,
                "HKD": 0.9357,
                "HNL": 0.2869,
                "HRK": 1.0126,
                "HTG": 0.0555,
                "HUF": 0.0186,
                "IDR": 0.0005,
                "IEP": 9.687,
                "ILS": 2.0228,
                "IMP": 9.1998,
                "INR": 0.0858,
                "IQD": 0.0055,
                "IRR": 0.0002,
                "ISK": 0.0522,
                "ITL": 0.0039,
                "JEP": 9.1998,
                "JMD": 0.0464,
                "JOD": 10.261,
                "JPY": 0.0474,
                "KES": 0.0561,
                "KGS": 0.0838,
                "KHR": 0.0018,
                "KMF": 0.0155,
                "KPW": 0.0081,
                "KRW": 0.0051,
                "KWD": 23.6319,
                "KYD": 8.7936,
                "KZT": 0.0139,
                "LAK": 0.0003,
                "LBP": 0.0001,
                "LINK": 209.2606,
                "LKR": 0.025,
                "LRD": 0.0405,
                "LSL": 0.4057,
                "LTC": 874.7605,
                "LTL": 2.2095,
                "LUF": 0.1891,
                "LUNA": 3.6243,
                "LVL": 10.8553,
                "LYD": 1.4909,
                "MAD": 0.7283,
                "MDL": 0.3972,
                "MGA": 0.0015,
                "MGF": 0.0003,
                "MKD": 0.1238,
                "MMK": 0.0035,
                "MNT": 0.0021,
                "MOP": 0.9084,
                "MRO": 0.0183,
                "MRU": 0.1831,
                "MTL": 17.771,
                "MUR": 0.1547,
                "MVR": 0.4713,
                "MWK": 0.0042,
                "MXN": 0.3597,
                "MXV": 2.9986,
                "MYR": 1.6346,
                "MZM": 0.0001,
                "MZN": 0.1139,
                "NAD": 0.4057,
                "NGN": 0.0047,
                "NIO": 0.1976,
                "NLG": 3.4619,
                "NOK": 0.6547,
                "NPR": 0.0536,
                "NZD": 4.1947,
                "OMR": 18.8963,
                "PAB": 7.2751,
                "PEN": 1.9444,
                "PGK": 1.8131,
                "PHP": 0.1241,
                "PKR": 0.0261,
                "PLN": 1.7857,
                "PTE": 0.0381,
                "PYG": 0.0009,
                "QAR": 1.9986,
                "ROL": 0.0002,
                "RON": 1.534,
                "RSD": 0.0652,
                "RUB": 0.0704,
                "RWF": 0.0052,
                "SAR": 1.94,
                "SBD": 0.869,
                "SCR": 0.5216,
                "SDD": 0.0001,
                "SDG": 0.0121,
                "SEK": 0.6627,
                "SGD": 5.3961,
                "SHP": 9.1998,
                "SIT": 0.0318,
                "SKK": 0.2532,
                "SLE": 0.3198,
                "SLL": 0.0003,
                "SOS": 0.0127,
                "SPL": 43.6503,
                "SRD": 0.2049,
                "SRG": 0.0002,
                "STD": 0.0003,
                "STN": 0.3103,
                "SVC": 0.8314,
                "SYP": 0.0006,
                "SZL": 0.4057,
                "THB": 0.2131,
                "TJS": 0.6651,
                "TMM": 0.0004,
                "TMT": 2.0731,
                "TND": 2.2973,
                "TOP": 3.0388,
                "TRL": 0.0,
                "TRY": 0.2082,
                "TTD": 1.0716,
                "TVD": 4.6357,
                "TWD": 0.2238,
                "TZS": 0.0028,
                "UAH": 0.1747,
                "UGX": 0.002,
                "UNI": 126.5967,
                "USD": 7.2751,
                "UYU": 0.1645,
                "UZS": 0.0006,
                "VAL": 0.0039,
                "VEB": 0.0,
                "VED": 0.146,
                "VEF": 0.0,
                "VES": 0.146,
                "VND": 0.0003,
                "VUV": 0.0598,
                "WST": 2.6124,
                "XAF": 0.0116,
                "XAG": 224.2806,
                "XAU": 19413.7061,
                "XBT": 729927.0073,
                "XCD": 2.688,
                "XDR": 9.5596,
                "XLM": 3.0708,
                "XOF": 0.0116,
                "XPD": 7105.8054,
                "XPF": 0.0639,
                "XPT": 6821.7477,
                "XRP": 16.9119,
                "YER": 0.0291,
                "ZAR": 0.4057,
                "ZMK": 0.0003,
                "ZMW": 0.2639,
                "ZWD": 0.0201,
                "ZWG": 0.2856,
                "ZWL": 0.0001
        }
}