{
  "date": "2026-05-27 02:00 GMT+8",
  "rates": {
    "ADA": 1.62844,
    "AED": 1.84886,
    "AFN": 0.10845,
    "ALL": 0.08276,
    "AMD": 0.01846,
    "ANG": 3.77071,
    "AOA": 0.00738,
    "ARB": 0.73364,
    "ARS": 0.00482,
    "ATS": 0.57355,
    "AUD": 4.86304,
    "AVAX": 62.30588,
    "AWG": 3.79326,
    "AZM": 0.0008,
    "AZN": 3.99407,
    "BAM": 4.03523,
    "BBD": 3.39497,
    "BCH": 2349.23767,
    "BDT": 0.05532,
    "BEF": 0.19564,
    "BGN": 4.03523,
    "BHD": 18.05834,
    "BIF": 0.00228,
    "BMD": 6.78994,
    "BNB": 4452.55799,
    "BND": 5.31347,
    "BOB": 0.98131,
    "BRL": 1.35093,
    "BSD": 6.78994,
    "BTC": 515463.91753,
    "BTN": 0.07094,
    "BWP": 0.50511,
    "BYN": 2.46916,
    "BYR": 0.00025,
    "BZD": 3.37232,
    "CAD": 4.91336,
    "CDF": 0.00297,
    "CHF": 8.63863,
    "CLF": 302.84034,
    "CLP": 0.00758,
    "CNH": 1.00041,
    "CNY": 1,
    "COP": 0.00185,
    "CRC": 0.01502,
    "CUC": 6.78994,
    "CUP": 0.28312,
    "CVE": 0.07157,
    "CYP": 13.48466,
    "CZK": 0.32525,
    "DAI": 6.78806,
    "DEM": 4.03523,
    "DJF": 0.03815,
    "DKK": 1.05612,
    "DOGE": 0.68641,
    "DOP": 0.11545,
    "DOT": 8.5277,
    "DZD": 0.05104,
    "EEK": 0.5044,
    "EGP": 0.13003,
    "ERN": 0.45266,
    "ESP": 0.04743,
    "ETB": 0.04223,
    "ETH": 14042.97149,
    "EUR": 7.89222,
    "EURC": 7.89776,
    "FIM": 1.32738,
    "FJD": 3.08117,
    "FKP": 9.12584,
    "FRF": 1.20316,
    "GBP": 9.12584,
    "GEL": 2.54705,
    "GGP": 9.12584,
    "GHC": 6e-05,
    "GHS": 0.58292,
    "GIP": 9.12584,
    "GMD": 0.09258,
    "GNF": 0.00077,
    "GRD": 0.02316,
    "GTQ": 0.8906,
    "GYD": 0.03246,
    "HKD": 0.86646,
    "HNL": 0.25528,
    "HRK": 1.04748,
    "HTG": 0.05194,
    "HUF": 0.02217,
    "IDR": 0.00038,
    "IEP": 10.02106,
    "ILS": 2.38665,
    "IMP": 9.12584,
    "INR": 0.07094,
    "IQD": 0.00518,
    "IRR": 1e-05,
    "ISK": 0.05511,
    "ITL": 0.00408,
    "JEP": 9.12584,
    "JMD": 0.04312,
    "JOD": 9.57678,
    "JPY": 0.0426,
    "KES": 0.05244,
    "KGS": 0.07763,
    "KHR": 0.00169,
    "KMF": 0.01604,
    "KPW": 0.00754,
    "KRW": 0.0045,
    "KWD": 21.94321,
    "KYD": 8.16403,
    "KZT": 0.01415,
    "LAK": 0.00031,
    "LBP": 8e-05,
    "LINK": 63.795,
    "LKR": 0.02068,
    "LRD": 0.03713,
    "LSL": 0.41424,
    "LTC": 351.69287,
    "LTL": 2.28575,
    "LUF": 0.19564,
    "LUNA": 0.37314,
    "LVL": 11.22969,
    "LYD": 1.06827,
    "MAD": 0.73906,
    "MDL": 0.39226,
    "MGA": 0.00162,
    "MGF": 0.00032,
    "MKD": 0.1281,
    "MMK": 0.00323,
    "MNT": 0.0019,
    "MOP": 0.84121,
    "MRO": 0.01701,
    "MRU": 0.17013,
    "MTL": 18.38423,
    "MUR": 0.1435,
    "MVR": 0.43972,
    "MWK": 0.00392,
    "MXN": 0.39217,
    "MXV": 3.47215,
    "MYR": 1.71208,
    "MZM": 0.00011,
    "MZN": 0.10634,
    "NAD": 0.4143,
    "NGN": 0.00495,
    "NIO": 0.18457,
    "NLG": 3.58139,
    "NOK": 0.73183,
    "NPR": 0.04432,
    "NZD": 3.96067,
    "OMR": 17.64216,
    "PAB": 6.78994,
    "PEN": 1.99011,
    "PGK": 1.55596,
    "PHP": 0.11024,
    "PKR": 0.02439,
    "PLN": 1.86251,
    "POL": 0.62192,
    "PTE": 0.03937,
    "PYG": 0.00111,
    "QAR": 1.86537,
    "ROL": 0.00015,
    "RON": 1.50646,
    "RSD": 0.06723,
    "RUB": 0.09444,
    "RWF": 0.00464,
    "SAR": 1.81065,
    "SBD": 0.84543,
    "SCR": 0.47581,
    "SDD": 0.00011,
    "SDG": 0.01131,
    "SEK": 0.72842,
    "SGD": 5.3138,
    "SHP": 9.12715,
    "SIT": 0.03293,
    "SKK": 0.26198,
    "SLE": 0.29706,
    "SLL": 0.0003,
    "SOL": 568.23025,
    "SOS": 0.0119,
    "SPL": 40.73962,
    "SRD": 0.18273,
    "SRG": 0.00018,
    "SSP": 0.00145,
    "STD": 0.00032,
    "STN": 0.31994,
    "SVC": 0.77599,
    "SYP": 0.06125,
    "SZL": 0.4143,
    "THB": 0.20774,
    "TJS": 0.73337,
    "TMM": 0.00039,
    "TMT": 1.94184,
    "TND": 2.34168,
    "TOP": 2.82311,
    "TRL": 0,
    "TRX": 2.5481,
    "TRY": 0.14792,
    "TTD": 1.00035,
    "TVD": 4.86354,
    "TWD": 0.21595,
    "TZS": 0.00259,
    "UAH": 0.15326,
    "UGX": 0.0018,
    "UNI": 22.22156,
    "USD": 6.78994,
    "USDC": 6.78892,
    "USDP": 6.78442,
    "USDT": 6.78093,
    "UYU": 0.16986,
    "UZS": 0.00057,
    "VAL": 0.00408,
    "VEB": 0,
    "VED": 0.01276,
    "VEF": 0,
    "VES": 0.01276,
    "VND": 0.00026,
    "VUV": 0.05726,
    "WST": 2.52658,
    "XAF": 0.01203,
    "XAG": 516.28358,
    "XAU": 30543.67746,
    "XBT": 515463.91753,
    "XCD": 2.50838,
    "XCG": 3.77127,
    "XDR": 9.29547,
    "XLM": 1.00306,
    "XOF": 0.01203,
    "XPD": 9361.54278,
    "XPF": 0.06614,
    "XPT": 13187.39285,
    "XRP": 9.05423,
    "YER": 0.02845,
    "ZAR": 0.4143,
    "ZMK": 0.00036,
    "ZMW": 0.36041,
    "ZWD": 0.01876,
    "ZWG": 0.25663,
    "ZWL": 0.0001
  }
}
