{
  "date": "2025-07-05 01:00 GMT+8",
  "rates": {
    "ADA": 4.29042,
    "AED": 1.95106,
    "AFN": 0.10259,
    "ALL": 0.08613,
    "AMD": 0.01869,
    "ANG": 3.97694,
    "AOA": 0.00779,
    "ARS": 0.00577,
    "ATS": 0.61314,
    "AUD": 4.69315,
    "AWG": 4.00295,
    "AZM": 0.00084,
    "AZN": 4.21487,
    "BAM": 4.31379,
    "BBD": 3.58264,
    "BCH": 3462.48399,
    "BDT": 0.05843,
    "BEF": 0.20915,
    "BGN": 4.31379,
    "BHD": 19.05661,
    "BIF": 0.00241,
    "BMD": 7.16529,
    "BND": 5.62252,
    "BOB": 1.03731,
    "BRL": 1.32423,
    "BSD": 7.16529,
    "BTC": 769230.76923,
    "BTN": 0.08383,
    "BWP": 0.54094,
    "BYN": 2.18789,
    "BYR": 0.00022,
    "BZD": 3.56133,
    "CAD": 5.26497,
    "CDF": 0.00246,
    "CHF": 9.03113,
    "CLF": 295.07665,
    "CLP": 0.00768,
    "CNH": 1.00013,
    "CNY": 1,
    "COP": 0.00179,
    "CRC": 0.01419,
    "CUC": 7.16529,
    "CUP": 0.29861,
    "CVE": 0.07651,
    "CYP": 14.41554,
    "CZK": 0.34253,
    "DEM": 4.31379,
    "DJF": 0.04024,
    "DKK": 1.13065,
    "DOGE": 1.16365,
    "DOP": 0.11989,
    "DOT": 23.90562,
    "DZD": 0.05537,
    "EEK": 0.53922,
    "EGP": 0.14516,
    "ERN": 0.47769,
    "ESP": 0.05071,
    "ETB": 0.05284,
    "ETH": 17825.31194,
    "EUR": 8.43704,
    "EURC": 8.10793,
    "FIM": 1.41901,
    "FJD": 3.19936,
    "FKP": 9.77782,
    "FRF": 1.28622,
    "GBP": 9.77782,
    "GEL": 2.63669,
    "GGP": 9.77782,
    "GHC": 7e-05,
    "GHS": 0.69233,
    "GIP": 9.77782,
    "GMD": 0.09939,
    "GNF": 0.00083,
    "GRD": 0.02476,
    "GTQ": 0.93201,
    "GYD": 0.03426,
    "HKD": 0.9128,
    "HNL": 0.27422,
    "HRK": 1.11987,
    "HTG": 0.0546,
    "HUF": 0.02118,
    "IDR": 0.00044,
    "IEP": 10.7136,
    "ILS": 2.14104,
    "IMP": 9.77746,
    "INR": 0.08383,
    "IQD": 0.00547,
    "IRR": 0.00017,
    "ISK": 0.05925,
    "ITL": 0.00436,
    "JEP": 9.77746,
    "JMD": 0.04484,
    "JOD": 10.10619,
    "JPY": 0.04959,
    "KES": 0.05547,
    "KGS": 0.08192,
    "KHR": 0.00178,
    "KMF": 0.01715,
    "KPW": 0.00796,
    "KRW": 0.00526,
    "KWD": 23.4707,
    "KYD": 8.63877,
    "KZT": 0.01379,
    "LAK": 0.00033,
    "LBP": 8e-05,
    "LINK": 93.40304,
    "LKR": 0.02389,
    "LRD": 0.03574,
    "LSL": 0.40648,
    "LTC": 619.44052,
    "LTL": 2.44371,
    "LUF": 0.20916,
    "LUNA": 0.96954,
    "LVL": 12.00576,
    "LYD": 1.33061,
    "MAD": 0.79762,
    "MDL": 0.4256,
    "MGA": 0.00163,
    "MGF": 0.00033,
    "MKD": 0.13718,
    "MMK": 0.00341,
    "MNT": 0.002,
    "MOP": 0.88621,
    "MRO": 0.01806,
    "MRU": 0.18056,
    "MTL": 19.65443,
    "MUR": 0.15945,
    "MVR": 0.46407,
    "MWK": 0.00413,
    "MXN": 0.38438,
    "MXV": 3.26888,
    "MYR": 1.69717,
    "MZM": 0.00011,
    "MZN": 0.11216,
    "NAD": 0.40648,
    "NGN": 0.00468,
    "NIO": 0.19475,
    "NLG": 3.82884,
    "NOK": 0.71121,
    "NPR": 0.05237,
    "NZD": 4.33795,
    "OMR": 18.6176,
    "PAB": 7.16529,
    "PEN": 2.01922,
    "PGK": 1.73551,
    "PHP": 0.12697,
    "PKR": 0.02524,
    "PLN": 1.98889,
    "PTE": 0.04209,
    "PYG": 0.0009,
    "QAR": 1.96849,
    "ROL": 0.00017,
    "RON": 1.66802,
    "RSD": 0.07201,
    "RUB": 0.09099,
    "RWF": 0.00499,
    "SAR": 1.91074,
    "SBD": 0.84172,
    "SCR": 0.49778,
    "SDD": 0.00012,
    "SDG": 0.01193,
    "SEK": 0.74924,
    "SGD": 5.62284,
    "SHP": 9.77746,
    "SIT": 0.03521,
    "SKK": 0.28008,
    "SLE": 0.31503,
    "SLL": 0.00032,
    "SOL": 1043.92851,
    "SOS": 0.01255,
    "SPL": 42.99171,
    "SRD": 0.19202,
    "SRG": 0.00019,
    "STD": 0.00034,
    "STN": 0.34252,
    "SVC": 0.81889,
    "SYP": 0.00055,
    "SZL": 0.40648,
    "THB": 0.22131,
    "TJS": 0.73705,
    "TMM": 0.00041,
    "TMT": 2.04278,
    "TND": 2.49366,
    "TOP": 2.97531,
    "TRL": 0,
    "TRY": 0.17976,
    "TTD": 1.0568,
    "TVD": 4.69326,
    "TWD": 0.24778,
    "TZS": 0.00271,
    "UAH": 0.17174,
    "UGX": 0.002,
    "UNI": 48.9175,
    "USD": 7.16529,
    "USDC": 7.22988,
    "USDP": 7.17818,
    "UYU": 0.17859,
    "UZS": 0.00057,
    "VAL": 0.00436,
    "VEB": 0,
    "VED": 0.06517,
    "VEF": 0,
    "VES": 0.06517,
    "VND": 0.00027,
    "VUV": 0.06015,
    "WST": 2.76111,
    "XAF": 0.01286,
    "XAG": 264.72675,
    "XAU": 23912.00383,
    "XBT": 769230.76923,
    "XCD": 2.64861,
    "XCG": 3.9768,
    "XDR": 9.86316,
    "XLM": 1.69968,
    "XOF": 0.01286,
    "XPD": 8153.2817,
    "XPF": 0.07071,
    "XPT": 9999.0001,
    "XRP": 15.83973,
    "YER": 0.02958,
    "ZAR": 0.40648,
    "ZMK": 0.00029,
    "ZMW": 0.29378,
    "ZWD": 0.0198,
    "ZWG": 0.26636,
    "ZWL": 0.00011
  }
}
