{
        "date": "2024/11/06 19:00 GMT+8",
        "rates": {
                "ADA": 2.5666,
                "AED": 1.9507,
                "AFN": 0.1069,
                "ALL": 0.0784,
                "AMD": 0.0185,
                "ANG": 3.9848,
                "AOA": 0.0078,
                "ARS": 0.0072,
                "ATS": 0.5597,
                "AUD": 4.7166,
                "AWG": 4.0022,
                "AZM": 0.0008,
                "AZN": 4.2141,
                "BAM": 3.9379,
                "BBD": 3.582,
                "BCH": 2663.4705,
                "BDT": 0.06,
                "BEF": 0.1909,
                "BGN": 3.9379,
                "BHD": 19.0531,
                "BIF": 0.0025,
                "BMD": 7.164,
                "BND": 5.3803,
                "BOB": 1.035,
                "BRL": 1.1959,
                "BSD": 7.164,
                "BTC": 529100.5291,
                "BTN": 0.085,
                "BWP": 0.5341,
                "BYN": 2.1908,
                "BYR": 0.0002,
                "BZD": 3.5458,
                "CAD": 5.1575,
                "CDF": 0.0025,
                "CHF": 8.1825,
                "CLF": 284.8492,
                "CLP": 0.0075,
                "CNH": 0.9971,
                "CNY": 1.0,
                "COP": 0.0016,
                "CRC": 0.014,
                "CUC": 7.164,
                "CUP": 0.2988,
                "CVE": 0.0698,
                "CYP": 13.1595,
                "CZK": 0.3038,
                "DEM": 3.9379,
                "DJF": 0.0403,
                "DKK": 1.0329,
                "DOGE": 1.4485,
                "DOP": 0.1187,
                "DOT": 29.3073,
                "DZD": 0.0535,
                "EEK": 0.4922,
                "EGP": 0.1456,
                "ERN": 0.4776,
                "ESP": 0.0463,
                "ETB": 0.0593,
                "ETH": 18811.1362,
                "EUR": 7.7019,
                "FIM": 1.2954,
                "FJD": 3.1795,
                "FKP": 9.2387,
                "FRF": 1.1741,
                "GBP": 9.2387,
                "GEL": 2.631,
                "GGP": 9.2387,
                "GHC": 0.0,
                "GHS": 0.4375,
                "GIP": 9.2387,
                "GMD": 0.1003,
                "GNF": 0.0008,
                "GRD": 0.0226,
                "GTQ": 0.9285,
                "GYD": 0.0343,
                "HKD": 0.9214,
                "HNL": 0.2847,
                "HRK": 1.0222,
                "HTG": 0.0545,
                "HUF": 0.0187,
                "IDR": 0.0005,
                "IEP": 9.7794,
                "ILS": 1.9153,
                "IMP": 9.2387,
                "INR": 0.085,
                "IQD": 0.0055,
                "IRR": 0.0002,
                "ISK": 0.0519,
                "ITL": 0.004,
                "JEP": 9.2387,
                "JMD": 0.0453,
                "JOD": 10.1043,
                "JPY": 0.0465,
                "KES": 0.0555,
                "KGS": 0.0831,
                "KHR": 0.0018,
                "KMF": 0.0157,
                "KPW": 0.008,
                "KRW": 0.0051,
                "KWD": 23.3381,
                "KYD": 8.6738,
                "KZT": 0.0145,
                "LAK": 0.0003,
                "LBP": 0.0001,
                "LINK": 84.7514,
                "LKR": 0.0245,
                "LRD": 0.0374,
                "LSL": 0.4054,
                "LTC": 500.6859,
                "LTL": 2.2306,
                "LUF": 0.1909,
                "LUNA": 2.375,
                "LVL": 10.9589,
                "LYD": 1.4863,
                "MAD": 0.7251,
                "MDL": 0.4009,
                "MGA": 0.0016,
                "MGF": 0.0003,
                "MKD": 0.1261,
                "MMK": 0.0034,
                "MNT": 0.0021,
                "MOP": 0.8946,
                "MRO": 0.018,
                "MRU": 0.1802,
                "MTL": 17.9406,
                "MUR": 0.1543,
                "MVR": 0.464,
                "MWK": 0.0041,
                "MXN": 0.347,
                "MXV": 2.9464,
                "MYR": 1.6271,
                "MZM": 0.0001,
                "MZN": 0.1121,
                "NAD": 0.4054,
                "NGN": 0.0043,
                "NIO": 0.1947,
                "NLG": 3.495,
                "NOK": 0.6479,
                "NPR": 0.0531,
                "NZD": 4.2751,
                "OMR": 18.6069,
                "PAB": 7.164,
                "PEN": 1.8995,
                "PGK": 1.7922,
                "PHP": 0.122,
                "PKR": 0.0258,
                "PLN": 1.7636,
                "PTE": 0.0384,
                "PYG": 0.0009,
                "QAR": 1.9681,
                "ROL": 0.0002,
                "RON": 1.5479,
                "RSD": 0.0658,
                "RUB": 0.073,
                "RWF": 0.0052,
                "SAR": 1.9104,
                "SBD": 0.8529,
                "SCR": 0.5264,
                "SDD": 0.0001,
                "SDG": 0.0119,
                "SEK": 0.662,
                "SGD": 5.3803,
                "SHP": 9.2387,
                "SIT": 0.0321,
                "SKK": 0.2557,
                "SLE": 0.3149,
                "SLL": 0.0003,
                "SOS": 0.0126,
                "SPL": 42.9838,
                "SRD": 0.2053,
                "SRG": 0.0002,
                "STD": 0.0003,
                "STN": 0.313,
                "SVC": 0.8187,
                "SYP": 0.0005,
                "SZL": 0.4054,
                "THB": 0.2096,
                "TJS": 0.6725,
                "TMM": 0.0004,
                "TMT": 2.0418,
                "TND": 2.3013,
                "TOP": 3.0159,
                "TRL": 0.0,
                "TRY": 0.2093,
                "TTD": 1.0574,
                "TVD": 4.7166,
                "TWD": 0.2222,
                "TZS": 0.0027,
                "UAH": 0.1728,
                "UGX": 0.0019,
                "UNI": 64.8821,
                "USD": 7.164,
                "UYU": 0.1722,
                "UZS": 0.0006,
                "VAL": 0.004,
                "VEB": 0.0,
                "VED": 0.1651,
                "VEF": 0.0,
                "VES": 0.1651,
                "VND": 0.0003,
                "VUV": 0.0598,
                "WST": 2.5971,
                "XAF": 0.0117,
                "XAG": 230.5619,
                "XAU": 19489.3783,
                "XBT": 529100.5291,
                "XCD": 2.6469,
                "XDR": 9.492,
                "XLM": 0.6926,
                "XOF": 0.0117,
                "XPD": 7613.247,
                "XPF": 0.0645,
                "XPT": 7101.7683,
                "XRP": 3.832,
                "YER": 0.0286,
                "ZAR": 0.4054,
                "ZMK": 0.0003,
                "ZMW": 0.266,
                "ZWD": 0.0198,
                "ZWG": 0.2756,
                "ZWL": 0.0001
        }
}