{
        "date": "2025/02/17 03:00 GMT+8",
        "rates": {
                "ADA": 5.5349,
                "AED": 1.975,
                "AFN": 0.0989,
                "ALL": 0.0767,
                "AMD": 0.0183,
                "ANG": 4.0244,
                "AOA": 0.008,
                "ARS": 0.0069,
                "ATS": 0.5525,
                "AUD": 4.608,
                "AWG": 4.0521,
                "AZM": 0.0009,
                "AZN": 4.2666,
                "BAM": 3.887,
                "BBD": 3.6266,
                "BCH": 2381.2359,
                "BDT": 0.0597,
                "BEF": 0.1885,
                "BGN": 3.887,
                "BHD": 19.2904,
                "BIF": 0.0025,
                "BMD": 7.2532,
                "BND": 5.4112,
                "BOB": 1.0489,
                "BRL": 1.2711,
                "BSD": 7.2532,
                "BTC": 704225.3521,
                "BTN": 0.0837,
                "BWP": 0.523,
                "BYN": 2.2148,
                "BYR": 0.0002,
                "BZD": 3.6065,
                "CAD": 5.1146,
                "CDF": 0.0025,
                "CHF": 8.0652,
                "CLF": 295.5257,
                "CLP": 0.0077,
                "CNH": 0.9992,
                "CNY": 1.0,
                "COP": 0.0018,
                "CRC": 0.0143,
                "CUC": 7.2532,
                "CUP": 0.3033,
                "CVE": 0.0689,
                "CYP": 12.9895,
                "CZK": 0.304,
                "DEM": 3.887,
                "DJF": 0.0407,
                "DKK": 1.0198,
                "DOGE": 1.9278,
                "DOP": 0.1167,
                "DOT": 35.3642,
                "DZD": 0.0535,
                "EEK": 0.4859,
                "EGP": 0.1432,
                "ERN": 0.4835,
                "ESP": 0.0457,
                "ETB": 0.0574,
                "ETH": 19432.569,
                "EUR": 7.6024,
                "FIM": 1.2786,
                "FJD": 3.155,
                "FKP": 9.1343,
                "FRF": 1.159,
                "GBP": 9.1343,
                "GEL": 2.5574,
                "GGP": 9.1343,
                "GHC": 0.0,
                "GHS": 0.4711,
                "GIP": 9.1343,
                "GMD": 0.1014,
                "GNF": 0.0008,
                "GRD": 0.0223,
                "GTQ": 0.9404,
                "GYD": 0.0347,
                "HKD": 0.9318,
                "HNL": 0.2836,
                "HRK": 1.009,
                "HTG": 0.0551,
                "HUF": 0.0189,
                "IDR": 0.0004,
                "IEP": 9.6531,
                "ILS": 2.0449,
                "IMP": 9.1343,
                "INR": 0.0837,
                "IQD": 0.0055,
                "IRR": 0.0002,
                "ISK": 0.0518,
                "ITL": 0.0039,
                "JEP": 9.1343,
                "JMD": 0.0461,
                "JOD": 10.2302,
                "JPY": 0.0476,
                "KES": 0.0561,
                "KGS": 0.0829,
                "KHR": 0.0018,
                "KMF": 0.0155,
                "KPW": 0.0081,
                "KRW": 0.005,
                "KWD": 23.4955,
                "KYD": 8.8451,
                "KZT": 0.0144,
                "LAK": 0.0003,
                "LBP": 0.0001,
                "LINK": 136.424,
                "LKR": 0.0243,
                "LRD": 0.0367,
                "LSL": 0.3949,
                "LTC": 916.5903,
                "LTL": 2.2018,
                "LUF": 0.1885,
                "LUNA": 2.3444,
                "LVL": 10.8173,
                "LYD": 1.4801,
                "MAD": 0.7277,
                "MDL": 0.3869,
                "MGA": 0.0015,
                "MGF": 0.0003,
                "MKD": 0.1239,
                "MMK": 0.0035,
                "MNT": 0.0021,
                "MOP": 0.9046,
                "MRO": 0.0181,
                "MRU": 0.1812,
                "MTL": 17.7088,
                "MUR": 0.1562,
                "MVR": 0.4692,
                "MWK": 0.0042,
                "MXN": 0.3568,
                "MXV": 2.9928,
                "MYR": 1.6353,
                "MZM": 0.0001,
                "MZN": 0.1141,
                "NAD": 0.3949,
                "NGN": 0.0048,
                "NIO": 0.1979,
                "NLG": 3.4498,
                "NOK": 0.6525,
                "NPR": 0.0523,
                "NZD": 4.1569,
                "OMR": 18.8422,
                "PAB": 7.2532,
                "PEN": 1.9544,
                "PGK": 1.8089,
                "PHP": 0.1257,
                "PKR": 0.026,
                "PLN": 1.8268,
                "PTE": 0.0379,
                "PYG": 0.0009,
                "QAR": 1.9926,
                "ROL": 0.0002,
                "RON": 1.5293,
                "RSD": 0.065,
                "RUB": 0.0796,
                "RWF": 0.0052,
                "SAR": 1.9342,
                "SBD": 0.8602,
                "SCR": 0.4914,
                "SDD": 0.0001,
                "SDG": 0.0121,
                "SEK": 0.6775,
                "SGD": 5.4112,
                "SHP": 9.1343,
                "SIT": 0.0317,
                "SKK": 0.2524,
                "SLE": 0.3181,
                "SLL": 0.0003,
                "SOS": 0.0127,
                "SPL": 43.5192,
                "SRD": 0.2073,
                "SRG": 0.0002,
                "STD": 0.0003,
                "STN": 0.3099,
                "SVC": 0.8289,
                "SYP": 0.0006,
                "SZL": 0.3949,
                "THB": 0.2154,
                "TJS": 0.6629,
                "TMM": 0.0004,
                "TMT": 2.0723,
                "TND": 2.2883,
                "TOP": 3.0261,
                "TRL": 0.0,
                "TRY": 0.2006,
                "TTD": 1.0716,
                "TVD": 4.608,
                "TWD": 0.2219,
                "TZS": 0.0028,
                "UAH": 0.1734,
                "UGX": 0.002,
                "UNI": 70.0082,
                "USD": 7.2532,
                "UYU": 0.1672,
                "UZS": 0.0006,
                "VAL": 0.0039,
                "VEB": 0.0,
                "VED": 0.117,
                "VEF": 0.0,
                "VES": 0.117,
                "VND": 0.0003,
                "VUV": 0.0589,
                "WST": 2.5683,
                "XAF": 0.0116,
                "XAG": 233.1568,
                "XAU": 20911.7524,
                "XBT": 704225.3521,
                "XCD": 2.6861,
                "XDR": 9.505,
                "XLM": 2.4893,
                "XOF": 0.0116,
                "XPD": 6963.3034,
                "XPF": 0.0637,
                "XPT": 7121.4927,
                "XRP": 19.6988,
                "YER": 0.0293,
                "ZAR": 0.3949,
                "ZMK": 0.0003,
                "ZMW": 0.2575,
                "ZWD": 0.02,
                "ZWG": 0.2705,
                "ZWL": 0.0001
        }
}