{
  "date": "2026-03-14 02:00 GMT+8",
  "rates": {
    "ADA": 1.84283,
    "AED": 1.8786,
    "AFN": 0.11012,
    "ALL": 0.08219,
    "AMD": 0.01828,
    "ANG": 3.82705,
    "AOA": 0.00752,
    "ARS": 0.00493,
    "ATS": 0.57366,
    "AUD": 4.83127,
    "AWG": 3.85427,
    "AZM": 0.00081,
    "AZN": 4.05834,
    "BAM": 4.03603,
    "BBD": 3.44957,
    "BCH": 3193.45979,
    "BDT": 0.05621,
    "BEF": 0.19568,
    "BGN": 4.03603,
    "BHD": 18.34879,
    "BIF": 0.00232,
    "BMD": 6.89914,
    "BNB": 4530.01133,
    "BND": 5.37814,
    "BOB": 0.99778,
    "BRL": 1.30269,
    "BSD": 6.89914,
    "BTC": 490196.07843,
    "BTN": 0.07459,
    "BWP": 0.5061,
    "BYN": 2.33475,
    "BYR": 0.00023,
    "BZD": 3.42705,
    "CAD": 5.02345,
    "CDF": 0.00303,
    "CHF": 8.73562,
    "CLF": 298.09191,
    "CLP": 0.00752,
    "CNH": 0.99912,
    "CNY": 1,
    "COP": 0.00186,
    "CRC": 0.01466,
    "CUC": 6.89914,
    "CUP": 0.28749,
    "CVE": 0.07159,
    "CYP": 13.48734,
    "CZK": 0.32235,
    "DEM": 4.03603,
    "DJF": 0.0388,
    "DKK": 1.05642,
    "DOGE": 0.66238,
    "DOP": 0.11165,
    "DOT": 10.2354,
    "DZD": 0.05204,
    "EEK": 0.5045,
    "EGP": 0.13174,
    "ERN": 0.45994,
    "ESP": 0.04744,
    "ETB": 0.04407,
    "ETH": 14467.59259,
    "EUR": 7.89379,
    "EURC": 7.9283,
    "FIM": 1.32764,
    "FJD": 3.10158,
    "FKP": 9.13799,
    "FRF": 1.2034,
    "GBP": 9.13799,
    "GEL": 2.52824,
    "GGP": 9.13799,
    "GHC": 6e-05,
    "GHS": 0.63442,
    "GIP": 9.13799,
    "GMD": 0.09344,
    "GNF": 0.00079,
    "GRD": 0.02317,
    "GTQ": 0.89971,
    "GYD": 0.03296,
    "HKD": 0.88131,
    "HNL": 0.26074,
    "HRK": 1.04769,
    "HTG": 0.05259,
    "HUF": 0.0201,
    "IDR": 0.00041,
    "IEP": 10.02305,
    "ILS": 2.19582,
    "IMP": 9.13799,
    "INR": 0.07459,
    "IQD": 0.00526,
    "IRR": 1e-05,
    "ISK": 0.05474,
    "ITL": 0.00408,
    "JEP": 9.13799,
    "JMD": 0.04397,
    "JOD": 9.73081,
    "JPY": 0.04323,
    "KES": 0.05339,
    "KGS": 0.07888,
    "KHR": 0.00172,
    "KMF": 0.01605,
    "KPW": 0.00767,
    "KRW": 0.0046,
    "KWD": 22.46885,
    "KYD": 8.29934,
    "KZT": 0.0141,
    "LAK": 0.00032,
    "LBP": 8e-05,
    "LINK": 62.96369,
    "LKR": 0.02216,
    "LRD": 0.03766,
    "LSL": 0.40806,
    "LTC": 381.63132,
    "LTL": 2.2862,
    "LUF": 0.19568,
    "LUNA": 0.44107,
    "LVL": 11.23192,
    "LYD": 1.08137,
    "MAD": 0.73127,
    "MDL": 0.39605,
    "MGA": 0.00166,
    "MGF": 0.00033,
    "MKD": 0.12805,
    "MMK": 0.00329,
    "MNT": 0.00193,
    "MOP": 0.85565,
    "MRO": 0.0172,
    "MRU": 0.172,
    "MTL": 18.38621,
    "MUR": 0.14902,
    "MVR": 0.44628,
    "MWK": 0.00397,
    "MXN": 0.3855,
    "MXV": 3.38584,
    "MYR": 1.75471,
    "MZM": 0.00011,
    "MZN": 0.10806,
    "NAD": 0.40804,
    "NGN": 0.00498,
    "NIO": 0.18766,
    "NLG": 3.58178,
    "NOK": 0.70764,
    "NPR": 0.0466,
    "NZD": 3.99928,
    "OMR": 17.926,
    "PAB": 6.89914,
    "PEN": 1.99917,
    "PGK": 1.60375,
    "PHP": 0.11544,
    "PKR": 0.0247,
    "PLN": 1.8456,
    "PTE": 0.03937,
    "PYG": 0.00107,
    "QAR": 1.89537,
    "ROL": 0.00015,
    "RON": 1.5491,
    "RSD": 0.06722,
    "RUB": 0.08613,
    "RWF": 0.00473,
    "SAR": 1.83977,
    "SBD": 0.85813,
    "SCR": 0.47696,
    "SDD": 0.00011,
    "SDG": 0.0115,
    "SEK": 0.73054,
    "SGD": 5.37841,
    "SHP": 9.13756,
    "SIT": 0.03294,
    "SKK": 0.26201,
    "SLE": 0.2998,
    "SLL": 0.0003,
    "SOL": 612.83147,
    "SOS": 0.01208,
    "SPL": 41.39486,
    "SRD": 0.18356,
    "SRG": 0.00018,
    "SSP": 0.00151,
    "STD": 0.00032,
    "STN": 0.32051,
    "SVC": 0.78847,
    "SYP": 0.06186,
    "SZL": 0.40804,
    "THB": 0.2128,
    "TJS": 0.71963,
    "TMM": 0.00039,
    "TMT": 1.9666,
    "TND": 2.33808,
    "TOP": 2.87743,
    "TRL": 0,
    "TRY": 0.15612,
    "TTD": 1.0173,
    "TVD": 4.83195,
    "TWD": 0.21488,
    "TZS": 0.00264,
    "UAH": 0.15627,
    "UGX": 0.00185,
    "UNI": 27.80027,
    "USD": 6.89914,
    "USDC": 6.89882,
    "USDP": 6.89604,
    "USDT": 6.90006,
    "UYU": 0.17083,
    "UZS": 0.00057,
    "VAL": 0.00408,
    "VEB": 0,
    "VED": 0.01563,
    "VEF": 0,
    "VES": 0.01563,
    "VND": 0.00026,
    "VUV": 0.0577,
    "WST": 2.52234,
    "XAF": 0.01203,
    "XAG": 558.31924,
    "XAU": 34818.9415,
    "XBT": 490196.07843,
    "XCD": 2.54828,
    "XCG": 3.82722,
    "XDR": 9.3687,
    "XLM": 1.12002,
    "XOF": 0.01203,
    "XPD": 10877.84184,
    "XPF": 0.06615,
    "XPT": 14144.27157,
    "XRP": 9.61996,
    "YER": 0.02892,
    "ZAR": 0.40804,
    "ZMK": 0.00036,
    "ZMW": 0.35538,
    "ZWD": 0.01906,
    "ZWG": 0.27085,
    "ZWL": 0.00011
  }
}
