{
  "date": "2025-07-07 15:00 GMT+8",
  "rates": {
    "ADA": 4.40698,
    "AED": 1.95327,
    "AFN": 0.10269,
    "ALL": 0.08609,
    "AMD": 0.01871,
    "ANG": 3.98145,
    "AOA": 0.00779,
    "ARS": 0.00578,
    "ATS": 0.61277,
    "AUD": 4.66856,
    "AWG": 4.00749,
    "AZM": 0.00084,
    "AZN": 4.21966,
    "BAM": 4.31114,
    "BBD": 3.5867,
    "BCH": 3567.0971,
    "BDT": 0.05852,
    "BEF": 0.20902,
    "BGN": 4.31114,
    "BHD": 19.07819,
    "BIF": 0.00241,
    "BMD": 7.1734,
    "BND": 5.61772,
    "BOB": 1.03764,
    "BRL": 1.32182,
    "BSD": 7.1734,
    "BTC": 781250,
    "BTN": 0.08358,
    "BWP": 0.539,
    "BYN": 2.19033,
    "BYR": 0.00022,
    "BZD": 3.56514,
    "CAD": 5.2568,
    "CDF": 0.00247,
    "CHF": 9.0204,
    "CLF": 295.85799,
    "CLP": 0.0077,
    "CNH": 0.99986,
    "CNY": 1,
    "COP": 0.0018,
    "CRC": 0.0142,
    "CUC": 7.1734,
    "CUP": 0.29924,
    "CVE": 0.07647,
    "CYP": 14.40669,
    "CZK": 0.3426,
    "DEM": 4.31114,
    "DJF": 0.04027,
    "DKK": 1.13008,
    "DOGE": 1.23819,
    "DOP": 0.11985,
    "DOT": 24.3245,
    "DZD": 0.05545,
    "EEK": 0.53889,
    "EGP": 0.14539,
    "ERN": 0.47823,
    "ESP": 0.05068,
    "ETB": 0.0529,
    "ETH": 18395.87932,
    "EUR": 8.43186,
    "EURC": 8.43399,
    "FIM": 1.41814,
    "FJD": 3.19201,
    "FKP": 9.764,
    "FRF": 1.28543,
    "GBP": 9.764,
    "GEL": 2.63988,
    "GGP": 9.764,
    "GHC": 7e-05,
    "GHS": 0.69318,
    "GIP": 9.764,
    "GMD": 0.09922,
    "GNF": 0.00083,
    "GRD": 0.02475,
    "GTQ": 0.93319,
    "GYD": 0.03428,
    "HKD": 0.91381,
    "HNL": 0.27452,
    "HRK": 1.1191,
    "HTG": 0.0545,
    "HUF": 0.02113,
    "IDR": 0.00044,
    "IEP": 10.70625,
    "ILS": 2.14796,
    "IMP": 9.764,
    "INR": 0.08358,
    "IQD": 0.00548,
    "IRR": 0.00017,
    "ISK": 0.05921,
    "ITL": 0.00435,
    "JEP": 9.7624,
    "JMD": 0.04492,
    "JOD": 10.11763,
    "JPY": 0.04944,
    "KES": 0.05553,
    "KGS": 0.08201,
    "KHR": 0.00179,
    "KMF": 0.01714,
    "KPW": 0.00797,
    "KRW": 0.00524,
    "KWD": 23.49142,
    "KYD": 8.63055,
    "KZT": 0.01381,
    "LAK": 0.00033,
    "LBP": 8e-05,
    "LINK": 98.12888,
    "LKR": 0.02388,
    "LRD": 0.03577,
    "LSL": 0.40377,
    "LTC": 628.19595,
    "LTL": 2.44192,
    "LUF": 0.20901,
    "LUNA": 0.99644,
    "LVL": 11.99693,
    "LYD": 1.33142,
    "MAD": 0.79902,
    "MDL": 0.42601,
    "MGA": 0.00163,
    "MGF": 0.00033,
    "MKD": 0.13711,
    "MMK": 0.00342,
    "MNT": 0.002,
    "MOP": 0.88719,
    "MRO": 0.01807,
    "MRU": 0.1807,
    "MTL": 19.63998,
    "MUR": 0.15952,
    "MVR": 0.46453,
    "MWK": 0.00413,
    "MXN": 0.38397,
    "MXV": 3.2743,
    "MYR": 1.69379,
    "MZM": 0.00011,
    "MZN": 0.11228,
    "NAD": 0.40377,
    "NGN": 0.00468,
    "NIO": 0.19491,
    "NLG": 3.82602,
    "NOK": 0.70891,
    "NPR": 0.0522,
    "NZD": 4.3109,
    "OMR": 18.64439,
    "PAB": 7.1734,
    "PEN": 2.02175,
    "PGK": 1.71232,
    "PHP": 0.1266,
    "PKR": 0.02526,
    "PLN": 1.98536,
    "PTE": 0.04206,
    "PYG": 0.0009,
    "QAR": 1.97071,
    "ROL": 0.00017,
    "RON": 1.66631,
    "RSD": 0.07196,
    "RUB": 0.09109,
    "RWF": 0.00499,
    "SAR": 1.91291,
    "SBD": 0.8422,
    "SCR": 0.49477,
    "SDD": 0.00012,
    "SDG": 0.01195,
    "SEK": 0.74972,
    "SGD": 5.6171,
    "SHP": 9.7624,
    "SIT": 0.03518,
    "SKK": 0.27987,
    "SLE": 0.31538,
    "SLL": 0.00032,
    "SOL": 1084.14011,
    "SOS": 0.01257,
    "SPL": 43.04039,
    "SRD": 0.19229,
    "SRG": 0.00019,
    "STD": 0.00034,
    "STN": 0.3417,
    "SVC": 0.81982,
    "SYP": 0.00055,
    "SZL": 0.40377,
    "THB": 0.21958,
    "TJS": 0.73775,
    "TMM": 0.00041,
    "TMT": 2.04445,
    "TND": 2.48462,
    "TOP": 2.97848,
    "TRL": 0,
    "TRY": 0.17945,
    "TTD": 1.05801,
    "TVD": 4.66746,
    "TWD": 0.24691,
    "TZS": 0.00272,
    "UAH": 0.17185,
    "UGX": 0.002,
    "UNI": 52.95738,
    "USD": 7.1734,
    "USDC": 7.23933,
    "USDP": 7.18057,
    "UYU": 0.17863,
    "UZS": 0.00057,
    "VAL": 0.00435,
    "VEB": 0,
    "VED": 0.06524,
    "VEF": 0,
    "VES": 0.06524,
    "VND": 0.00027,
    "VUV": 0.06036,
    "WST": 2.61755,
    "XAF": 0.01285,
    "XAG": 262.55678,
    "XAU": 23747.32843,
    "XBT": 781250,
    "XCD": 2.64978,
    "XCG": 3.97949,
    "XDR": 9.87432,
    "XLM": 1.80039,
    "XOF": 0.01285,
    "XPD": 7942.18092,
    "XPF": 0.07066,
    "XPT": 9730.46609,
    "XRP": 16.21406,
    "YER": 0.02962,
    "ZAR": 0.40377,
    "ZMK": 0.00029,
    "ZMW": 0.2946,
    "ZWD": 0.01982,
    "ZWG": 0.26675,
    "ZWL": 0.00011
  }
}
