{
  "date": "2025-10-31 22:00 GMT+8",
  "rates": {
    "ADA": 4.4071,
    "AED": 1.93833,
    "AFN": 0.10662,
    "ALL": 0.08487,
    "AMD": 0.01862,
    "ANG": 3.94694,
    "AOA": 0.00778,
    "ARS": 0.00494,
    "ATS": 0.59705,
    "AUD": 4.65896,
    "AWG": 3.97682,
    "AZM": 0.00084,
    "AZN": 4.18735,
    "BAM": 4.20053,
    "BBD": 3.55925,
    "BCH": 3943.83972,
    "BDT": 0.05821,
    "BEF": 0.20366,
    "BGN": 4.20053,
    "BHD": 18.93218,
    "BIF": 0.00241,
    "BMD": 7.1185,
    "BND": 5.46887,
    "BOB": 1.0294,
    "BRL": 1.3229,
    "BSD": 7.1185,
    "BTC": 781250,
    "BTN": 0.08021,
    "BWP": 0.51198,
    "BYN": 2.09055,
    "BYR": 0.00021,
    "BZD": 3.53504,
    "CAD": 5.0757,
    "CDF": 0.0031,
    "CHF": 8.85247,
    "CLF": 296.46847,
    "CLP": 0.00756,
    "CNH": 0.9995,
    "CNY": 1,
    "COP": 0.00184,
    "CRC": 0.01419,
    "CUC": 7.1185,
    "CUP": 0.29637,
    "CVE": 0.0745,
    "CYP": 14.03706,
    "CZK": 0.33754,
    "DEM": 4.20053,
    "DJF": 0.03996,
    "DKK": 1.10013,
    "DOGE": 1.32598,
    "DOP": 0.11077,
    "DOT": 20.67136,
    "DZD": 0.05475,
    "EEK": 0.52507,
    "EGP": 0.15069,
    "ERN": 0.47457,
    "ESP": 0.04938,
    "ETB": 0.04626,
    "ETH": 27449.90393,
    "EUR": 8.21552,
    "EURC": 8.22348,
    "FIM": 1.38175,
    "FJD": 3.10431,
    "FKP": 9.33527,
    "FRF": 1.25245,
    "GBP": 9.33527,
    "GEL": 2.62525,
    "GGP": 9.33527,
    "GHC": 7e-05,
    "GHS": 0.65321,
    "GIP": 9.33527,
    "GMD": 0.09754,
    "GNF": 0.00082,
    "GRD": 0.02411,
    "GTQ": 0.92861,
    "GYD": 0.03399,
    "HKD": 0.91606,
    "HNL": 0.2706,
    "HRK": 1.09039,
    "HTG": 0.05436,
    "HUF": 0.02117,
    "IDR": 0.00043,
    "IEP": 10.43156,
    "ILS": 2.1907,
    "IMP": 9.33527,
    "INR": 0.08021,
    "IQD": 0.00543,
    "IRR": 0.00017,
    "ISK": 0.05673,
    "ITL": 0.00424,
    "JEP": 9.33527,
    "JMD": 0.04437,
    "JOD": 10.0402,
    "JPY": 0.0462,
    "KES": 0.05509,
    "KGS": 0.08139,
    "KHR": 0.00177,
    "KMF": 0.0167,
    "KPW": 0.00791,
    "KRW": 0.00498,
    "KWD": 23.1983,
    "KYD": 8.55718,
    "KZT": 0.01343,
    "LAK": 0.00033,
    "LBP": 8e-05,
    "LINK": 122.75301,
    "LKR": 0.02336,
    "LRD": 0.03881,
    "LSL": 0.41002,
    "LTC": 676.19196,
    "LTL": 2.37938,
    "LUF": 0.20366,
    "LUNA": 0.66674,
    "LVL": 11.6897,
    "LYD": 1.30578,
    "MAD": 0.76592,
    "MDL": 0.41796,
    "MGA": 0.00158,
    "MGF": 0.00032,
    "MKD": 0.13349,
    "MMK": 0.00339,
    "MNT": 0.00198,
    "MOP": 0.88937,
    "MRO": 0.01787,
    "MRU": 0.17875,
    "MTL": 19.13702,
    "MUR": 0.15545,
    "MVR": 0.46218,
    "MWK": 0.0041,
    "MXN": 0.38337,
    "MXV": 3.28583,
    "MYR": 1.6996,
    "MZM": 0.00011,
    "MZN": 0.11139,
    "NAD": 0.41002,
    "NGN": 0.00492,
    "NIO": 0.19341,
    "NLG": 3.72804,
    "NOK": 0.7057,
    "NPR": 0.05011,
    "NZD": 4.07444,
    "OMR": 18.49477,
    "PAB": 7.1185,
    "PEN": 2.10333,
    "PGK": 1.68651,
    "PHP": 0.12121,
    "PKR": 0.02515,
    "PLN": 1.92985,
    "PTE": 0.04098,
    "PYG": 0.001,
    "QAR": 1.95563,
    "ROL": 0.00016,
    "RON": 1.6154,
    "RSD": 0.0701,
    "RUB": 0.0881,
    "RWF": 0.0049,
    "SAR": 1.89827,
    "SBD": 0.83763,
    "SCR": 0.51685,
    "SDD": 0.00012,
    "SDG": 0.01184,
    "SEK": 0.75213,
    "SGD": 5.46887,
    "SHP": 9.33527,
    "SIT": 0.03428,
    "SKK": 0.27271,
    "SLE": 0.31387,
    "SLL": 0.00031,
    "SOL": 1340.12329,
    "SOS": 0.01233,
    "SPL": 42.711,
    "SRD": 0.18482,
    "SRG": 0.00018,
    "STD": 0.00033,
    "STN": 0.33321,
    "SVC": 0.81354,
    "SYP": 0.00064,
    "SZL": 0.41002,
    "THB": 0.22013,
    "TJS": 0.77215,
    "TMM": 0.00041,
    "TMT": 2.0349,
    "TND": 2.41416,
    "TOP": 2.95614,
    "TRL": 0,
    "TRY": 0.16938,
    "TTD": 1.05041,
    "TVD": 4.65896,
    "TWD": 0.23156,
    "TZS": 0.00289,
    "UAH": 0.16956,
    "UGX": 0.00205,
    "UNI": 40.9238,
    "USD": 7.1185,
    "USDC": 7.15943,
    "USDP": 7.11031,
    "UYU": 0.17843,
    "UZS": 0.00059,
    "VAL": 0.00424,
    "VEB": 0,
    "VED": 0.03219,
    "VEF": 0,
    "VES": 0.03219,
    "VND": 0.00027,
    "VUV": 0.0584,
    "WST": 2.54277,
    "XAF": 0.01252,
    "XAG": 347.84061,
    "XAU": 28587.76444,
    "XBT": 781250,
    "XCD": 2.62978,
    "XCG": 3.94694,
    "XDR": 9.68089,
    "XLM": 2.19215,
    "XOF": 0.01252,
    "XPD": 10424.2677,
    "XPF": 0.06885,
    "XPT": 11354.60429,
    "XRP": 17.85727,
    "YER": 0.02985,
    "ZAR": 0.41002,
    "ZMK": 0.00032,
    "ZMW": 0.32033,
    "ZWD": 0.01967,
    "ZWG": 0.26843,
    "ZWL": 0.00011
  }
}
