{
        "date": "2024/12/11 00:00 GMT+8",
        "rates": {
                "ADA": 7.0901,
                "AED": 1.9743,
                "AFN": 0.1052,
                "ALL": 0.0777,
                "AMD": 0.0184,
                "ANG": 4.0294,
                "AOA": 0.0079,
                "ARS": 0.0071,
                "ATS": 0.5533,
                "AUD": 4.6197,
                "AWG": 4.0506,
                "AZM": 0.0009,
                "AZN": 4.265,
                "BAM": 3.8926,
                "BBD": 3.6252,
                "BCH": 3662.7353,
                "BDT": 0.0606,
                "BEF": 0.1887,
                "BGN": 3.8926,
                "BHD": 19.2832,
                "BIF": 0.0025,
                "BMD": 7.2505,
                "BND": 5.3983,
                "BOB": 1.0482,
                "BRL": 1.199,
                "BSD": 7.2505,
                "BTC": 699300.6993,
                "BTN": 0.0854,
                "BWP": 0.5344,
                "BYN": 2.2172,
                "BYR": 0.0002,
                "BZD": 3.5871,
                "CAD": 5.1135,
                "CDF": 0.0025,
                "CHF": 8.2145,
                "CLF": 285.5454,
                "CLP": 0.0074,
                "CNH": 0.9982,
                "CNY": 1.0,
                "COP": 0.0017,
                "CRC": 0.0143,
                "CUC": 7.2505,
                "CUP": 0.3017,
                "CVE": 0.069,
                "CYP": 13.0081,
                "CZK": 0.3034,
                "DEM": 3.8926,
                "DJF": 0.0407,
                "DKK": 1.0209,
                "DOGE": 2.7805,
                "DOP": 0.1196,
                "DOT": 57.898,
                "DZD": 0.0542,
                "EEK": 0.4866,
                "EGP": 0.1437,
                "ERN": 0.4834,
                "ESP": 0.0458,
                "ETB": 0.0571,
                "ETH": 25879.9172,
                "EUR": 7.6133,
                "FIM": 1.2805,
                "FJD": 3.1464,
                "FKP": 9.2296,
                "FRF": 1.1606,
                "GBP": 9.2296,
                "GEL": 2.583,
                "GGP": 9.2296,
                "GHC": 0.0,
                "GHS": 0.4915,
                "GIP": 9.2296,
                "GMD": 0.1009,
                "GNF": 0.0008,
                "GRD": 0.0223,
                "GTQ": 0.9401,
                "GYD": 0.0347,
                "HKD": 0.9324,
                "HNL": 0.2859,
                "HRK": 1.0105,
                "HTG": 0.0553,
                "HUF": 0.0185,
                "IDR": 0.0005,
                "IEP": 9.6669,
                "ILS": 2.0187,
                "IMP": 9.2296,
                "INR": 0.0854,
                "IQD": 0.0055,
                "IRR": 0.0002,
                "ISK": 0.0522,
                "ITL": 0.0039,
                "JEP": 9.2296,
                "JMD": 0.0461,
                "JOD": 10.2264,
                "JPY": 0.0477,
                "KES": 0.056,
                "KGS": 0.0835,
                "KHR": 0.0018,
                "KMF": 0.0155,
                "KPW": 0.0081,
                "KRW": 0.0051,
                "KWD": 23.5657,
                "KYD": 8.7707,
                "KZT": 0.0142,
                "LAK": 0.0003,
                "LBP": 0.0001,
                "LINK": 156.006,
                "LKR": 0.025,
                "LRD": 0.0404,
                "LSL": 0.4057,
                "LTC": 766.5831,
                "LTL": 2.205,
                "LUF": 0.1887,
                "LUNA": 3.4647,
                "LVL": 10.8328,
                "LYD": 1.4846,
                "MAD": 0.7241,
                "MDL": 0.395,
                "MGA": 0.0015,
                "MGF": 0.0003,
                "MKD": 0.1241,
                "MMK": 0.0035,
                "MNT": 0.0021,
                "MOP": 0.9052,
                "MRO": 0.0182,
                "MRU": 0.1825,
                "MTL": 17.7343,
                "MUR": 0.1558,
                "MVR": 0.4698,
                "MWK": 0.0042,
                "MXN": 0.3575,
                "MXV": 2.9974,
                "MYR": 1.6378,
                "MZM": 0.0001,
                "MZN": 0.1135,
                "NAD": 0.4057,
                "NGN": 0.0046,
                "NIO": 0.1969,
                "NLG": 3.4548,
                "NOK": 0.649,
                "NPR": 0.0534,
                "NZD": 4.204,
                "OMR": 18.8332,
                "PAB": 7.2505,
                "PEN": 1.949,
                "PGK": 1.8003,
                "PHP": 0.1249,
                "PKR": 0.0261,
                "PLN": 1.7877,
                "PTE": 0.038,
                "PYG": 0.0009,
                "QAR": 1.9919,
                "ROL": 0.0002,
                "RON": 1.5317,
                "RSD": 0.0651,
                "RUB": 0.0707,
                "RWF": 0.0052,
                "SAR": 1.9335,
                "SBD": 0.8661,
                "SCR": 0.5213,
                "SDD": 0.0001,
                "SDG": 0.0121,
                "SEK": 0.6597,
                "SGD": 5.3983,
                "SHP": 9.2296,
                "SIT": 0.0318,
                "SKK": 0.2527,
                "SLE": 0.3187,
                "SLL": 0.0003,
                "SOS": 0.0127,
                "SPL": 43.503,
                "SRD": 0.2042,
                "SRG": 0.0002,
                "STD": 0.0003,
                "STN": 0.3092,
                "SVC": 0.8286,
                "SYP": 0.0006,
                "SZL": 0.4057,
                "THB": 0.2142,
                "TJS": 0.6649,
                "TMM": 0.0004,
                "TMT": 2.0662,
                "TND": 2.2964,
                "TOP": 3.0296,
                "TRL": 0.0,
                "TRY": 0.2081,
                "TTD": 1.0678,
                "TVD": 4.6197,
                "TWD": 0.2227,
                "TZS": 0.0028,
                "UAH": 0.1743,
                "UGX": 0.002,
                "UNI": 107.2991,
                "USD": 7.2505,
                "UYU": 0.1657,
                "UZS": 0.0006,
                "VAL": 0.0039,
                "VEB": 0.0,
                "VED": 0.1486,
                "VEF": 0.0,
                "VES": 0.1486,
                "VND": 0.0003,
                "VUV": 0.0596,
                "WST": 2.604,
                "XAF": 0.0116,
                "XAG": 231.4349,
                "XAU": 19474.1967,
                "XBT": 699300.6993,
                "XCD": 2.6795,
                "XDR": 9.5483,
                "XLM": 2.7704,
                "XOF": 0.0116,
                "XPD": 7016.0668,
                "XPF": 0.0638,
                "XPT": 6811.0612,
                "XRP": 14.9145,
                "YER": 0.029,
                "ZAR": 0.4057,
                "ZMK": 0.0003,
                "ZMW": 0.2645,
                "ZWD": 0.02,
                "ZWG": 0.2846,
                "ZWL": 0.0001
        }
}