{
  "date": "2026-02-17 04:00 GMT+8",
  "rates": {
    "ADA": 1.95387,
    "AED": 1.88147,
    "AFN": 0.10797,
    "ALL": 0.085,
    "AMD": 0.0183,
    "ANG": 3.83369,
    "AOA": 0.00755,
    "ARS": 0.00494,
    "ATS": 0.59525,
    "AUD": 4.88889,
    "AWG": 3.86017,
    "AZM": 0.00081,
    "AZN": 4.06453,
    "BAM": 4.18788,
    "BBD": 3.45485,
    "BCH": 3949.91508,
    "BDT": 0.05648,
    "BEF": 0.20304,
    "BGN": 4.18788,
    "BHD": 18.37686,
    "BIF": 0.00233,
    "BMD": 6.9097,
    "BNB": 4266.57565,
    "BND": 5.47286,
    "BOB": 0.99642,
    "BRL": 1.32016,
    "BSD": 6.9097,
    "BTC": 469483.56808,
    "BTN": 0.07613,
    "BWP": 0.52556,
    "BYN": 2.42446,
    "BYR": 0.00024,
    "BZD": 3.43129,
    "CAD": 5.06752,
    "CDF": 0.00301,
    "CHF": 8.98182,
    "CLF": 316.20553,
    "CLP": 0.00801,
    "CNH": 1.0036,
    "CNY": 1,
    "COP": 0.00189,
    "CRC": 0.01433,
    "CUC": 6.9097,
    "CUP": 0.28787,
    "CVE": 0.07428,
    "CYP": 13.99477,
    "CZK": 0.33761,
    "DEM": 4.18788,
    "DJF": 0.03884,
    "DKK": 1.09636,
    "DOGE": 0.69379,
    "DOP": 0.11111,
    "DOT": 9.38931,
    "DZD": 0.05326,
    "EEK": 0.52348,
    "EGP": 0.14791,
    "ERN": 0.46065,
    "ESP": 0.04923,
    "ETB": 0.04441,
    "ETH": 13659.33616,
    "EUR": 8.19077,
    "EURC": 8.18524,
    "FIM": 1.37759,
    "FJD": 3.14946,
    "FKP": 9.41947,
    "FRF": 1.24868,
    "GBP": 9.41947,
    "GEL": 2.58013,
    "GGP": 9.41947,
    "GHC": 6e-05,
    "GHS": 0.62827,
    "GIP": 9.41947,
    "GMD": 0.09354,
    "GNF": 0.00079,
    "GRD": 0.02404,
    "GTQ": 0.90089,
    "GYD": 0.03302,
    "HKD": 0.88405,
    "HNL": 0.26144,
    "HRK": 1.0871,
    "HTG": 0.05277,
    "HUF": 0.0217,
    "IDR": 0.00041,
    "IEP": 10.40014,
    "ILS": 2.23416,
    "IMP": 9.41947,
    "INR": 0.07613,
    "IQD": 0.00527,
    "IRR": 1e-05,
    "ISK": 0.05649,
    "ITL": 0.00423,
    "JEP": 9.41947,
    "JMD": 0.04417,
    "JOD": 9.7457,
    "JPY": 0.04502,
    "KES": 0.05355,
    "KGS": 0.079,
    "KHR": 0.00172,
    "KMF": 0.01665,
    "KPW": 0.00768,
    "KRW": 0.00479,
    "KWD": 22.53854,
    "KYD": 8.30694,
    "KZT": 0.01406,
    "LAK": 0.00032,
    "LBP": 8e-05,
    "LINK": 60.8112,
    "LKR": 0.02233,
    "LRD": 0.03714,
    "LSL": 0.43256,
    "LTC": 375.02766,
    "LTL": 2.37221,
    "LUF": 0.20304,
    "LUNA": 0.45949,
    "LVL": 11.65449,
    "LYD": 1.09564,
    "MAD": 0.7568,
    "MDL": 0.40723,
    "MGA": 0.00158,
    "MGF": 0.00032,
    "MKD": 0.13285,
    "MMK": 0.00329,
    "MNT": 0.00194,
    "MOP": 0.8583,
    "MRO": 0.01732,
    "MRU": 0.17322,
    "MTL": 19.07937,
    "MUR": 0.15051,
    "MVR": 0.44716,
    "MWK": 0.00398,
    "MXN": 0.40262,
    "MXV": 3.50299,
    "MYR": 1.77152,
    "MZM": 0.00011,
    "MZN": 0.10833,
    "NAD": 0.43256,
    "NGN": 0.00511,
    "NIO": 0.18775,
    "NLG": 3.71681,
    "NOK": 0.72751,
    "NPR": 0.04756,
    "NZD": 4.16953,
    "OMR": 17.95393,
    "PAB": 6.9097,
    "PEN": 2.06162,
    "PGK": 1.60134,
    "PHP": 0.11922,
    "PKR": 0.02471,
    "PLN": 1.94402,
    "PTE": 0.04086,
    "PYG": 0.00106,
    "QAR": 1.89827,
    "ROL": 0.00016,
    "RON": 1.60754,
    "RSD": 0.06977,
    "RUB": 0.09001,
    "RWF": 0.00474,
    "SAR": 1.84259,
    "SBD": 0.86008,
    "SCR": 0.49773,
    "SDD": 0.00012,
    "SDG": 0.01152,
    "SEK": 0.77277,
    "SGD": 5.47286,
    "SHP": 9.41947,
    "SIT": 0.03418,
    "SKK": 0.27188,
    "SLE": 0.30042,
    "SLL": 0.0003,
    "SOL": 585.83338,
    "SOS": 0.01211,
    "SPL": 41.45818,
    "SRD": 0.18306,
    "SRG": 0.00018,
    "SSP": 0.00152,
    "STD": 0.00033,
    "STN": 0.33159,
    "SVC": 0.78968,
    "SYP": 0.0625,
    "SZL": 0.43256,
    "THB": 0.2219,
    "TJS": 0.73225,
    "TMM": 0.0004,
    "TMT": 1.97675,
    "TND": 2.42475,
    "TOP": 2.86961,
    "TRL": 0,
    "TRY": 0.15807,
    "TTD": 1.01891,
    "TVD": 4.88868,
    "TWD": 0.22018,
    "TZS": 0.00265,
    "UAH": 0.15992,
    "UGX": 0.00195,
    "UNI": 24.29928,
    "USD": 6.9097,
    "USDC": 6.91005,
    "USDP": 6.89899,
    "USDT": 6.90694,
    "UYU": 0.17784,
    "UZS": 0.00057,
    "VAL": 0.00423,
    "VEB": 0,
    "VED": 0.01752,
    "VEF": 0,
    "VES": 0.01752,
    "VND": 0.00027,
    "VUV": 0.05807,
    "WST": 2.55451,
    "XAF": 0.01249,
    "XAG": 529.39744,
    "XAU": 34494.65333,
    "XBT": 469483.56808,
    "XCD": 2.55322,
    "XCG": 3.83441,
    "XDR": 9.52384,
    "XLM": 1.16085,
    "XOF": 0.01249,
    "XPD": 12088.97485,
    "XPF": 0.06863,
    "XPT": 14144.27157,
    "XRP": 10.20839,
    "YER": 0.02898,
    "ZAR": 0.43258,
    "ZMK": 0.00038,
    "ZMW": 0.37755,
    "ZWD": 0.01909,
    "ZWG": 0.27014,
    "ZWL": 0.00011
  }
}
